MANIFEST.in
README.rst
setup.py
collective/.DS_Store
collective/__init__.py
collective/__init__.pyc
collective.ptg.nivogallery.egg-info/PKG-INFO
collective.ptg.nivogallery.egg-info/SOURCES.txt
collective.ptg.nivogallery.egg-info/dependency_links.txt
collective.ptg.nivogallery.egg-info/entry_points.txt
collective.ptg.nivogallery.egg-info/namespace_packages.txt
collective.ptg.nivogallery.egg-info/not-zip-safe
collective.ptg.nivogallery.egg-info/requires.txt
collective.ptg.nivogallery.egg-info/top_level.txt
collective/ptg/.DS_Store
collective/ptg/__init__.py
collective/ptg/__init__.pyc
collective/ptg/nivogallery/.DS_Store
collective/ptg/nivogallery/__init__.py
collective/ptg/nivogallery/__init__.pyc
collective/ptg/nivogallery/configure.zcml
collective/ptg/nivogallery/i18n.sh
collective/ptg/nivogallery/nivogallery.pt
collective/ptg/nivogallery/locales/.DS_Store
collective/ptg/nivogallery/locales/collective.ptg.nivogallery.pot
collective/ptg/nivogallery/locales/manual.pot
collective/ptg/nivogallery/locales/de/LC_MESSAGES/collective.ptg.nivogallery.mo
collective/ptg/nivogallery/locales/de/LC_MESSAGES/collective.ptg.nivogallery.po
collective/ptg/nivogallery/locales/es/LC_MESSAGES/collective.ptg.nivogallery.mo
collective/ptg/nivogallery/locales/es/LC_MESSAGES/collective.ptg.nivogallery.po
collective/ptg/nivogallery/locales/eu/LC_MESSAGES/collective.ptg.nivogallery.mo
collective/ptg/nivogallery/locales/eu/LC_MESSAGES/collective.ptg.nivogallery.po
collective/ptg/nivogallery/locales/fi/LC_MESSAGES/collective.ptg.nivogallery.mo
collective/ptg/nivogallery/locales/fi/LC_MESSAGES/collective.ptg.nivogallery.po
collective/ptg/nivogallery/locales/fr/LC_MESSAGES/collective.ptg.nivogallery.mo
collective/ptg/nivogallery/locales/fr/LC_MESSAGES/collective.ptg.nivogallery.po
collective/ptg/nivogallery/locales/it/LC_MESSAGES/collective.ptg.nivogallery.mo
collective/ptg/nivogallery/locales/it/LC_MESSAGES/collective.ptg.nivogallery.po
collective/ptg/nivogallery/locales/nl/LC_MESSAGES/collective.ptg.nivogallery.mo
collective/ptg/nivogallery/locales/nl/LC_MESSAGES/collective.ptg.nivogallery.po
collective/ptg/nivogallery/locales/no/.DS_Store
collective/ptg/nivogallery/locales/no/LC_MESSAGES/.DS_Store
collective/ptg/nivogallery/locales/no/LC_MESSAGES/collective.ptg.nivogallery.mo
collective/ptg/nivogallery/locales/no/LC_MESSAGES/collective.ptg.nivogallery.po
