Metadata-Version: 1.0
Name: collective.ptg.nivogallery
Version: 1.1
Summary: nivo gallery integration with collective.plonetruegallery
Home-page: https://github.com/vangheem/collective.ptg.nivogallery
Author: Nathan Van Gheem
Author-email: vangheem@gmail.com
License: GPL
Keywords: plone plonetruegallery addon nivo gallery
Platform: UNKNOWN
Classifier: Framework :: Plone
Classifier: Programming Language :: Python
